SuperGLU/__init__.py
SuperGLU/Core/BlackWhiteListEntry.py
SuperGLU/Core/ClassifierEngine.py
SuperGLU/Core/Messaging.py
SuperGLU/Core/MessagingDB.py
SuperGLU/Core/MessagingGateway.py
SuperGLU/Core/ProposalUseCasesTest.py
SuperGLU/Core/ServiceConfiguration.py
SuperGLU/Core/ServiceLauncher.py
SuperGLU/Core/__init__.py
SuperGLU/Core/FIPA/SpeechActs.py
SuperGLU/Core/FIPA/__init__.py
SuperGLU/Core/Tests/ClassifierEngine_UnitTests.py
SuperGLU/Core/Tests/Messaging_UnitTests.py
SuperGLU/Core/Tests/ServiceLauncherTest.py
SuperGLU/Core/Tests/Suite.py
SuperGLU/Core/Tests/__init__.py
SuperGLU/Core/xAPI/TinCanEntities.py
SuperGLU/Core/xAPI/TinCanHelperClasses.py
SuperGLU/Core/xAPI/TinCanStatement.py
SuperGLU/Core/xAPI/TinCanVerb.py
SuperGLU/Core/xAPI/TinCanVocabulary.py
SuperGLU/Core/xAPI/__init__.py
SuperGLU/Examples/ASSISTmentsForET/ChildWindow.html
SuperGLU/Examples/ASSISTmentsForET/LoggerWindow.html
SuperGLU/Examples/ASSISTmentsForET/ParentPage.html
SuperGLU/Examples/ASSISTmentsForET/js/reference-data.js
SuperGLU/Examples/ASSISTmentsForET/js/SuperGLU/super-glu.js
SuperGLU/Examples/ASSISTmentsForET/js/SuperGLU/Core/messaging-gateway.js
SuperGLU/Examples/ASSISTmentsForET/js/SuperGLU/Core/messaging.js
SuperGLU/Examples/ASSISTmentsForET/js/SuperGLU/Services/LoggingService/standard-its-logging.js
SuperGLU/Examples/ASSISTmentsForET/js/SuperGLU/Services/Orchestration/heartbeat-service.js
SuperGLU/Examples/ASSISTmentsForET/js/SuperGLU/Util/emacs5-compatibility-patches.js
SuperGLU/Examples/ASSISTmentsForET/js/SuperGLU/Util/encoder.js
SuperGLU/Examples/ASSISTmentsForET/js/SuperGLU/Util/general-utilities.js
SuperGLU/Examples/ASSISTmentsForET/js/SuperGLU/Util/serialization.js
SuperGLU/Examples/ASSISTmentsForET/js/SuperGLU/Util/uuid.js
SuperGLU/Examples/ASSISTmentsForET/js/SuperGLU/Util/zet.js
SuperGLU/Examples/GIFTAssessment/GIFTAssessment.html
SuperGLU/Examples/GIFTAssessment/css/login.css
SuperGLU/Examples/GIFTAssessment/js/jquery.min.js
SuperGLU-0.1.8.dist-info/METADATA
SuperGLU-0.1.8.dist-info/RECORD
SuperGLU-0.1.8.dist-info/WHEEL
SuperGLU-0.1.8.dist-info/top_level.txt
