Metadata-Version: 2.1
Name: SuperGLU
Version: 0.1.8
Summary: Base Generalized Learning Utilities (GLU) library for communicating data between different learning technologies and intelligent systems.
Home-page: https://github.com/GeneralizedLearningUtilities/SuperGLU
Author: Benjamin D. Nye
Author-email: benjamin.nye@gmail.com
License: UNKNOWN
Download-URL: https://github.com/GeneralizedLearningUtilities/SuperGLU/archive/0.1.tar.gz
Keywords: ITS,Adaptive Learning,Messaging,HTML5,Websockets,Service
Platform: UNKNOWN
Classifier: License :: OSI Approved :: Apache Software License
Classifier: Programming Language :: Python
Classifier: Programming Language :: JavaScript
Classifier: Development Status :: 3 - Alpha
Classifier: Intended Audience :: Science/Research
